README.md
setup.py
scNodes/__init__.py
scNodes/__main__.py
scNodes/install.py
scNodes.egg-info/PKG-INFO
scNodes.egg-info/SOURCES.txt
scNodes.egg-info/dependency_links.txt
scNodes.egg-info/entry_points.txt
scNodes.egg-info/requires.txt
scNodes.egg-info/top_level.txt
scNodes/ceplugins/__init__.py
scNodes/ceplugins/apply_binning.py
scNodes/ceplugins/blur_image.py
scNodes/ceplugins/custom_plugin_template.py
scNodes/ceplugins/grayscalereg.py
scNodes/ceplugins/load_overview_map.py
scNodes/ceplugins/rotate_all.py
scNodes/ceplugins/split_rgb.py
scNodes/core/__init__.py
scNodes/core/ceplugin.py
scNodes/core/clemframe.py
scNodes/core/config.py
scNodes/core/correlation_editor.py
scNodes/core/datatypes.py
scNodes/core/extract.py
scNodes/core/imageviewer.py
scNodes/core/node.py
scNodes/core/nodeeditor.py
scNodes/core/opengl_classes.py
scNodes/core/particlefitting.py
scNodes/core/reconstruction.py
scNodes/core/roi.py
scNodes/core/settings.py
scNodes/core/util.py
scNodes/core/widgets.py
scNodes/core/window.py
scNodes/icons/LOGO_Pom_1024.png
scNodes/icons/LOGO_Pom_128.png
scNodes/icons/LOGO_Pom_2048.png
scNodes/icons/LOGO_Pom_256.png
scNodes/icons/LOGO_Pom_512.png
scNodes/icons/__init__.py
scNodes/icons/icon_blender_256.png
scNodes/icons/icon_chimerax_256.png
scNodes/icons/icon_close_256.png
scNodes/icons/icon_crop_256.png
scNodes/icons/icon_expand_256.png
scNodes/icons/icon_expanded_256.png
scNodes/icons/icon_jumpto_256.png
scNodes/icons/icon_linterp_256.png
scNodes/icons/icon_location_256.png
scNodes/icons/icon_locked_256.png
scNodes/icons/icon_ninterp_256.png
scNodes/icons/icon_obj_256.png
scNodes/icons/icon_pivot_256.png
scNodes/icons/icon_rotate_256.png
scNodes/icons/icon_scale_256.png
scNodes/icons/icon_stop_256.png
scNodes/icons/icon_unlocked_256.png
scNodes/icons/scnodes_boot_img.png
scNodes/nodes/__init__.py
scNodes/nodes/bakestack.py
scNodes/nodes/binimage.py
scNodes/nodes/cnnnode.py
scNodes/nodes/compile_trainset.py
scNodes/nodes/cropimage.py
scNodes/nodes/custom_node_template.py
scNodes/nodes/diagnostic_plots.py
scNodes/nodes/exportdata.py
scNodes/nodes/frameshift.py
scNodes/nodes/getimage.py
scNodes/nodes/imagecalculator.py
