Metadata-Version: 1.0
Name: scNodes
Version: 1.2.4
Summary: Correlating super-resolution fluorescence and cryoEM github.com/bionanopatterning/scNodes
Home-page: https://github.com/bionanopatterning/scNodes
Author: mgflast
Author-email: m.g.f.last@lumc.nl
License: GPL v3
Platform: UNKNOWN
